auto_model_monitor/__init__.py
auto_model_monitor/config.py
auto_model_monitor/monitor.py
auto_model_monitor/notifier.py
auto_model_monitor/parser.py
auto_model_monitor/utils.py
auto_model_monitor-0.2.2.dist-info/METADATA
auto_model_monitor-0.2.2.dist-info/WHEEL
auto_model_monitor-0.2.2.dist-info/top_level.txt
auto_model_monitor-0.2.2.dist-info/RECORD
