Metadata-Version: 2.1
Name: auto-model-monitor
Version: 0.2.2
Summary: A tool for monitoring model checkpoints and sending notifications
Home-page: https://github.com/Knighthood2001/model_monitor
Author: knighthood2001
Author-email: 2109695291@qq.com
License: UNKNOWN
Platform: UNKNOWN
Classifier: Programming Language :: Python :: 3
Classifier: License :: OSI Approved :: MIT License
Classifier: Operating System :: OS Independent
Requires-Python: >=3.7
Requires-Dist: yagmail
